aiohttp_cache/__init__.py
aiohttp_cache/backends.py
aiohttp_cache/decorators.py
aiohttp_cache/exceptions.py
aiohttp_cache/middleware.py
aiohttp_cache/py.typed
aiohttp_cache/setup.py
aiohttp_cache-4.0.1.dist-info/LICENSE
aiohttp_cache-4.0.1.dist-info/METADATA
aiohttp_cache-4.0.1.dist-info/WHEEL
aiohttp_cache-4.0.1.dist-info/RECORD
