Metadata-Version: 2.1
Name: aiohttp-cache
Version: 4.0.1
Summary: A cache system for aiohttp server
Home-page: https://github.com/cr0hn/aiohttp-cache
License: BSD
Author: Daniel Garcia (cr0hn)
Author-email: cr0hn@cr0hn.com
Maintainer: Daniel Garcia (cr0hn)
Maintainer-email: cr0hn@cr0hn.com
Requires-Python: >=3.7,<4.0
Classifier: Environment :: Console
Classifier: Intended Audience :: Other Audience
Classifier: Intended Audience :: System Administrators
Classifier: License :: OSI Approved :: BSD License
Classifier: License :: Other/Proprietary License
Classifier: Operating System :: MacOS
Classifier: Operating System :: Microsoft :: Windows
Classifier: Operating System :: POSIX
Classifier: Programming Language :: Python :: 3
Classifier: Programming Language :: Python :: 3.7
Classifier: Programming Language :: Python :: 3.8
Classifier: Programming Language :: Python :: 3.9
Classifier: Programming Language :: Python :: 3.10
Classifier: Programming Language :: Python :: 3.11
Classifier: Topic :: Security
Requires-Dist: aiohttp (>=3.6,<4.0)
Requires-Dist: envparse (>=0.2.0,<0.3.0)
Requires-Dist: redis (>=4.5.1,<5.0.0)
Project-URL: Repository, https://github.com/cr0hn/aiohttp-cache
